androbuilder/__init__.py
androbuilder/builder.py
androbuilder/cli.py
androbuilder/exceptions.py
androbuilder/ndk_manager.py
androbuilder/sdk_manager.py
androbuilder-1.0.0.dist-info/licenses/LICENSE
androbuilder-1.0.0.dist-info/METADATA
androbuilder-1.0.0.dist-info/WHEEL
androbuilder-1.0.0.dist-info/entry_points.txt
androbuilder-1.0.0.dist-info/top_level.txt
androbuilder-1.0.0.dist-info/RECORD
