Metadata-Version: 2.4
Name: androbuilder
Version: 1.0.0
Summary: A pure Python Android APK builder with auto SDK/NDK management
Home-page: https://github.com/RustamovHumoyunMirzo/androbuilder
Author: Rustamov Humoyun Mirzo
License: MIT
Project-URL: Homepage, https://github.com/RustamovHumoyunMirzo/androbuilder
Classifier: Programming Language :: Python :: 3
Classifier: License :: OSI Approved :: MIT License
Classifier: Operating System :: OS Independent
Classifier: Development Status :: 4 - Beta
Classifier: Intended Audience :: Developers
Classifier: Topic :: Software Development :: Build Tools
Requires-Python: >=3.7
License-File: LICENSE
Requires-Dist: requests>=2.25.0
Dynamic: home-page
Dynamic: license-file
Dynamic: requires-python
